firefeed_core/__init__.py
firefeed_core/di_container.py
firefeed_core/api_client/__init__.py
firefeed_core/api_client/circuit_breaker.py
firefeed_core/api_client/client.py
firefeed_core/api_client/rate_limiter.py
firefeed_core/api_client/retry.py
firefeed_core/auth/__init__.py
firefeed_core/auth/permissions.py
firefeed_core/auth/token_manager.py
firefeed_core/auth/token_validator.py
firefeed_core/config/__init__.py
firefeed_core/config/base_config.py
firefeed_core/config/logging_config.py
firefeed_core/config/redis_config.py
firefeed_core/config/redis_utils.py
firefeed_core/config/services_config.py
firefeed_core/config/settings.py
firefeed_core/config/validation.py
firefeed_core/email_service/__init__.py
firefeed_core/email_service/sender.py
firefeed_core/exceptions/__init__.py
firefeed_core/exceptions/api_exceptions.py
firefeed_core/exceptions/base_exceptions.py
firefeed_core/exceptions/database_exceptions.py
firefeed_core/exceptions/rss_exceptions.py
firefeed_core/exceptions/service_exceptions.py
firefeed_core/interfaces/__init__.py
firefeed_core/interfaces/base_interfaces.py
firefeed_core/interfaces/core_interfaces.py
firefeed_core/interfaces/email_interfaces.py
firefeed_core/interfaces/media_interfaces.py
firefeed_core/interfaces/repository_interfaces.py
firefeed_core/interfaces/rss_interfaces.py
firefeed_core/interfaces/telegram_interfaces.py
firefeed_core/interfaces/text_analysis_interfaces.py
firefeed_core/interfaces/translation_interfaces.py
firefeed_core/interfaces/user_interfaces.py
firefeed_core/models/__init__.py
firefeed_core/models/api_key_models.py
firefeed_core/models/base_models.py
firefeed_core/models/category_models.py
firefeed_core/models/error_models.py
firefeed_core/models/media_models.py
firefeed_core/models/rss_models.py
firefeed_core/models/source_models.py
firefeed_core/models/telegram_models.py
firefeed_core/models/translation_models.py
firefeed_core/models/user_models.py
firefeed_core/services/email_service.py
firefeed_core-1.0.0.dist-info/licenses/LICENSE
firefeed_core-1.0.0.dist-info/METADATA
firefeed_core-1.0.0.dist-info/WHEEL
firefeed_core-1.0.0.dist-info/top_level.txt
firefeed_core-1.0.0.dist-info/RECORD
