Metadata-Version: 2.4
Name: firefeed_core
Version: 1.0.0
Summary: Core utilities and models for FireFeed microservices
Author-email: FireFeed <mail@firefeed.net>
License: MIT
Project-URL: Homepage, https://firefeed.net
Project-URL: Repository, https://github.com/firefeed-net/firefeed-core
Project-URL: Documentation, https://docs.firefeed.net
Project-URL: Bug Tracker, https://github.com/firefeed-net/firefeed-core/issues
Keywords: firefeed,microservices,core,rss,news
Classifier: Development Status :: 4 - Beta
Classifier: Intended Audience :: Developers
Classifier: License :: OSI Approved :: MIT License
Classifier: Programming Language :: Python :: 3
Classifier: Programming Language :: Python :: 3.13
Requires-Python: >=3.13
License-File: LICENSE
Requires-Dist: pydantic>=2.0.0
Requires-Dist: pydantic-settings>=2.0.0
Requires-Dist: python-dotenv>=1.0.0
Requires-Dist: httpx>=0.25.0
Requires-Dist: PyJWT>=2.8.0
Requires-Dist: typing-extensions>=4.5.0
Requires-Dist: datetime
Requires-Dist: jinja2>=3.1.0
Requires-Dist: aiosmtplib>=2.0.0
Provides-Extra: dev
Requires-Dist: pytest>=7.0.0; extra == "dev"
Requires-Dist: pytest-asyncio>=0.21.0; extra == "dev"
Requires-Dist: pytest-cov>=4.0.0; extra == "dev"
Requires-Dist: black>=23.0.0; extra == "dev"
Requires-Dist: isort>=5.12.0; extra == "dev"
Requires-Dist: mypy>=1.5.0; extra == "dev"
Requires-Dist: flake8>=6.0.0; extra == "dev"
Requires-Dist: pre-commit>=3.0.0; extra == "dev"
Provides-Extra: test
Requires-Dist: pytest>=7.0.0; extra == "test"
Requires-Dist: pytest-asyncio>=0.21.0; extra == "test"
Requires-Dist: pytest-cov>=4.0.0; extra == "test"
Requires-Dist: pytest-mock>=3.11.0; extra == "test"
Dynamic: license-file
